{
    "child_model_execute_cost_by_ms": [
        14.119000434875488,
        8.444999694824219
    ],
    "child_model_run_time": [
        [
            23364548,
            23378667
        ],
        [
            23378778,
            23387223
        ]
    ],
    "execute_cost": 22.56399917602539,
    "finish_time": 23387232,
    "limit_cost_by_ms": 18.21500015258789,
    "model_name": "resnet50",
    "recv_time": 23364534,
    "tag": "706",
    "total_cost_by_ms": 22.697999954223633,
    "wait_cost": 0.1340007781982422
}
