{
    "child_model_execute_cost_by_ms": [
        14.052000045776367,
        8.611000061035156
    ],
    "child_model_run_time": [
        [
            23993563,
            24007615
        ],
        [
            24007660,
            24016271
        ]
    ],
    "execute_cost": 22.663000106811523,
    "finish_time": 24016278,
    "limit_cost_by_ms": 18.21500015258789,
    "model_name": "resnet50",
    "recv_time": 23993446,
    "tag": "736",
    "total_cost_by_ms": 22.832000732421875,
    "wait_cost": 0.16900062561035156
}
