{
    "child_model_execute_cost_by_ms": [
        18.679000854492188,
        18.611000061035156,
        19.11400032043457
    ],
    "child_model_run_time": [
        [
            27987790,
            28006469
        ],
        [
            28023553,
            28042164
        ],
        [
            28042208,
            28061322
        ]
    ],
    "execute_cost": 56.40399932861328,
    "finish_time": 28061330,
    "limit_cost_by_ms": 44.6870002746582,
    "model_name": "vgg19",
    "recv_time": 27987686,
    "tag": "926",
    "total_cost_by_ms": 73.64399719238281,
    "wait_cost": 17.23999786376953
}
