{
    "child_model_execute_cost_by_ms": [
        18.135000228881836,
        18.481000900268555,
        20.481000900268555
    ],
    "child_model_run_time": [
        [
            12683294,
            12701429
        ],
        [
            12726071,
            12744552
        ],
        [
            12744585,
            12765066
        ]
    ],
    "execute_cost": 57.09700012207031,
    "finish_time": 12765072,
    "limit_cost_by_ms": 47.42533493041992,
    "model_name": "vgg19",
    "recv_time": 12683286,
    "tag": "159",
    "total_cost_by_ms": 81.78600311279297,
    "wait_cost": 24.689002990722656
}
