{
    "child_model_execute_cost_by_ms": [
        18.149999618530273,
        17.576000213623047,
        20.95199966430664
    ],
    "child_model_run_time": [
        [
            13517203,
            13535353
        ],
        [
            13535395,
            13552971
        ],
        [
            13578015,
            13598967
        ]
    ],
    "execute_cost": 56.67799758911133,
    "finish_time": 13598974,
    "limit_cost_by_ms": 47.42533493041992,
    "model_name": "vgg19",
    "recv_time": 13510097,
    "tag": "193",
    "total_cost_by_ms": 88.87699890136719,
    "wait_cost": 32.19900131225586
}
