{
    "child_model_execute_cost_by_ms": [
        18.781999588012695,
        19.63599967956543,
        21.65399932861328
    ],
    "child_model_run_time": [
        [
            26585615,
            26604397
        ],
        [
            26638810,
            26658446
        ],
        [
            26658574,
            26680228
        ]
    ],
    "execute_cost": 60.071998596191406,
    "finish_time": 26680238,
    "limit_cost_by_ms": 47.42533493041992,
    "model_name": "vgg19",
    "recv_time": 26585459,
    "tag": "706",
    "total_cost_by_ms": 94.77899932861328,
    "wait_cost": 34.707000732421875
}
