{
    "child_model_execute_cost_by_ms": [
        19.64699935913086,
        19.440000534057617,
        21.23900032043457
    ],
    "child_model_run_time": [
        [
            27230412,
            27250059
        ],
        [
            27260387,
            27279827
        ],
        [
            27279917,
            27301156
        ]
    ],
    "execute_cost": 60.32599639892578,
    "finish_time": 27301164,
    "limit_cost_by_ms": 47.42533493041992,
    "model_name": "vgg19",
    "recv_time": 27230264,
    "tag": "732",
    "total_cost_by_ms": 70.9000015258789,
    "wait_cost": 10.574005126953125
}
