{
    "child_model_execute_cost_by_ms": [
        14.753000259399414,
        9.493000030517578
    ],
    "child_model_run_time": [
        [
            31626820,
            31641573
        ],
        [
            31641612,
            31651105
        ]
    ],
    "execute_cost": 24.246000289916992,
    "finish_time": 31651111,
    "limit_cost_by_ms": 19.129667282104492,
    "model_name": "resnet50",
    "recv_time": 31611620,
    "tag": "904",
    "total_cost_by_ms": 39.49100112915039,
    "wait_cost": 15.245000839233398
}
