{
    "child_model_execute_cost_by_ms": [
        15.407999992370605,
        9.284000396728516
    ],
    "child_model_run_time": [
        [
            14656089,
            14671497
        ],
        [
            14671538,
            14680822
        ]
    ],
    "execute_cost": 24.692001342773438,
    "finish_time": 14680831,
    "limit_cost_by_ms": 19.097999572753906,
    "model_name": "resnet50",
    "recv_time": 14653176,
    "tag": "276",
    "total_cost_by_ms": 27.655000686645508,
    "wait_cost": 2.9629993438720703
}
