{
    "child_model_execute_cost_by_ms": [
        18.788999557495117,
        17.48200035095215,
        20.072999954223633
    ],
    "child_model_run_time": [
        [
            16220768,
            16239557
        ],
        [
            16239596,
            16257078
        ],
        [
            16281407,
            16301480
        ]
    ],
    "execute_cost": 56.34400177001953,
    "finish_time": 16301491,
    "limit_cost_by_ms": 46.779998779296875,
    "model_name": "vgg19",
    "recv_time": 16220747,
    "tag": "350",
    "total_cost_by_ms": 80.74400329589844,
    "wait_cost": 24.400001525878906
}
