{
    "child_model_execute_cost_by_ms": [
        14.77400016784668,
        8.767999649047852
    ],
    "child_model_run_time": [
        [
            18820894,
            18835668
        ],
        [
            18843544,
            18852312
        ]
    ],
    "execute_cost": 23.54199981689453,
    "finish_time": 18852318,
    "limit_cost_by_ms": 19.097999572753906,
    "model_name": "resnet50",
    "recv_time": 18820808,
    "tag": "470",
    "total_cost_by_ms": 31.510000228881836,
    "wait_cost": 7.968000411987305
}
