{
    "child_model_execute_cost_by_ms": [
        2.996000051498413,
        4.39300012588501
    ],
    "child_model_run_time": [
        [
            19284467,
            19287463
        ],
        [
            19287507,
            19291900
        ]
    ],
    "execute_cost": 7.388999938964844,
    "finish_time": 19291906,
    "limit_cost_by_ms": 6.171000003814697,
    "model_name": "yolov2",
    "recv_time": 19284376,
    "tag": "492",
    "total_cost_by_ms": 7.53000020980835,
    "wait_cost": 0.14100027084350586
}
