{
    "child_model_execute_cost_by_ms": [
        19.392000198364258,
        17.680999755859375,
        20.030000686645508
    ],
    "child_model_run_time": [
        [
            27931958,
            27951350
        ],
        [
            27951402,
            27969083
        ],
        [
            27969134,
            27989164
        ]
    ],
    "execute_cost": 57.102996826171875,
    "finish_time": 27989171,
    "limit_cost_by_ms": 46.779998779296875,
    "model_name": "vgg19",
    "recv_time": 27917306,
    "tag": "893",
    "total_cost_by_ms": 71.86499786376953,
    "wait_cost": 14.762001037597656
}
