{
    "child_model_execute_cost_by_ms": [
        18.19300079345703,
        17.51799964904785,
        19.67099952697754
    ],
    "child_model_run_time": [
        [
            13957585,
            13975778
        ],
        [
            13975810,
            13993328
        ],
        [
            13993355,
            14013026
        ]
    ],
    "execute_cost": 55.381996154785156,
    "finish_time": 14013033,
    "limit_cost_by_ms": 47.01599884033203,
    "model_name": "vgg19",
    "recv_time": 13957576,
    "tag": "226",
    "total_cost_by_ms": 55.457000732421875,
    "wait_cost": 0.07500457763671875
}
