{
    "child_model_execute_cost_by_ms": [
        19.952999114990234,
        18.347999572753906,
        20.163000106811523
    ],
    "child_model_run_time": [
        [
            18291870,
            18311823
        ],
        [
            18311920,
            18330268
        ],
        [
            18330316,
            18350479
        ]
    ],
    "execute_cost": 58.46399688720703,
    "finish_time": 18350487,
    "limit_cost_by_ms": 47.01599884033203,
    "model_name": "vgg19",
    "recv_time": 18287205,
    "tag": "408",
    "total_cost_by_ms": 63.28200149536133,
    "wait_cost": 4.818004608154297
}
