{
    "child_model_execute_cost_by_ms": [
        16.0,
        9.550000190734863
    ],
    "child_model_run_time": [
        [
            24950845,
            24966845
        ],
        [
            24975305,
            24984855
        ]
    ],
    "execute_cost": 25.549999237060547,
    "finish_time": 24984868,
    "limit_cost_by_ms": 19.020000457763672,
    "model_name": "resnet50",
    "recv_time": 24933059,
    "tag": "683",
    "total_cost_by_ms": 51.808998107910156,
    "wait_cost": 26.25899887084961
}
