{
    "child_model_execute_cost_by_ms": [
        17.954999923706055,
        17.80500030517578,
        20.812000274658203
    ],
    "child_model_run_time": [
        [
            29921087,
            29939042
        ],
        [
            29939085,
            29956890
        ],
        [
            29965367,
            29986179
        ]
    ],
    "execute_cost": 56.57200241088867,
    "finish_time": 29986186,
    "limit_cost_by_ms": 47.01599884033203,
    "model_name": "vgg19",
    "recv_time": 29921043,
    "tag": "888",
    "total_cost_by_ms": 65.14299774169922,
    "wait_cost": 8.570995330810547
}
