{
    "child_model_execute_cost_by_ms": [
        2.9519999027252197,
        4.091000080108643
    ],
    "child_model_run_time": [
        [
            17495470,
            17498422
        ],
        [
            17498474,
            17502565
        ]
    ],
    "execute_cost": 7.043000221252441,
    "finish_time": 17502572,
    "limit_cost_by_ms": 6.240333557128906,
    "model_name": "yolov2",
    "recv_time": 17489697,
    "tag": "439",
    "total_cost_by_ms": 12.875,
    "wait_cost": 5.831999778747559
}
