{
    "child_model_execute_cost_by_ms": [
        19.040000915527344,
        17.253999710083008,
        19.336000442504883
    ],
    "child_model_run_time": [
        [
            9814274,
            9833314
        ],
        [
            9841006,
            9858260
        ],
        [
            9858346,
            9877682
        ]
    ],
    "execute_cost": 55.62999725341797,
    "finish_time": 9877690,
    "limit_cost_by_ms": 47.3489990234375,
    "model_name": "vgg19",
    "recv_time": 9814257,
    "tag": "61",
    "total_cost_by_ms": 63.43299865722656,
    "wait_cost": 7.803001403808594
}
