{
    "child_model_execute_cost_by_ms": [
        15.27299976348877,
        9.394000053405762
    ],
    "child_model_run_time": [
        [
            15294612,
            15309885
        ],
        [
            15309949,
            15319343
        ]
    ],
    "execute_cost": 24.66699981689453,
    "finish_time": 15319354,
    "limit_cost_by_ms": 19.095333099365234,
    "model_name": "resnet50",
    "recv_time": 15278032,
    "tag": "270",
    "total_cost_by_ms": 41.321998596191406,
    "wait_cost": 16.654998779296875
}
