{
    "child_model_execute_cost_by_ms": [
        15.157999992370605,
        8.956000328063965
    ],
    "child_model_run_time": [
        [
            25312569,
            25327727
        ],
        [
            25327766,
            25336722
        ]
    ],
    "execute_cost": 24.11400032043457,
    "finish_time": 25336730,
    "limit_cost_by_ms": 19.095333099365234,
    "model_name": "resnet50",
    "recv_time": 25312551,
    "tag": "660",
    "total_cost_by_ms": 24.179000854492188,
    "wait_cost": 0.06500053405761719
}
