{
    "child_model_execute_cost_by_ms": [
        18.823999404907227,
        19.860000610351563,
        21.111000061035156
    ],
    "child_model_run_time": [
        [
            16404890,
            16423714
        ],
        [
            16457192,
            16477052
        ],
        [
            16487263,
            16508374
        ]
    ],
    "execute_cost": 59.79499816894531,
    "finish_time": 16508384,
    "limit_cost_by_ms": 47.4206657409668,
    "model_name": "vgg19",
    "recv_time": 16404877,
    "tag": "382",
    "total_cost_by_ms": 103.50700378417969,
    "wait_cost": 43.712005615234375
}
