{
    "child_model_execute_cost_by_ms": [
        3.184000015258789,
        4.311999797821045
    ],
    "child_model_run_time": [
        [
            18758643,
            18761827
        ],
        [
            18761919,
            18766231
        ]
    ],
    "execute_cost": 7.495999813079834,
    "finish_time": 18766243,
    "limit_cost_by_ms": 6.208000183105469,
    "model_name": "yolov2",
    "recv_time": 18749096,
    "tag": "550",
    "total_cost_by_ms": 17.14699935913086,
    "wait_cost": 9.650999069213867
}
