{
    "child_model_execute_cost_by_ms": [
        15.220999717712402,
        9.295999526977539
    ],
    "child_model_run_time": [
        [
            26219102,
            26234323
        ],
        [
            26234420,
            26243716
        ]
    ],
    "execute_cost": 24.516998291015625,
    "finish_time": 26243728,
    "limit_cost_by_ms": 19.033666610717773,
    "model_name": "resnet50",
    "recv_time": 26200148,
    "tag": "950",
    "total_cost_by_ms": 43.58000183105469,
    "wait_cost": 19.063003540039063
}
