{
    "child_model_execute_cost_by_ms": [
        19.466999053955078,
        19.06800079345703,
        20.74799919128418
    ],
    "child_model_run_time": [
        [
            13750667,
            13770134
        ],
        [
            13795289,
            13814357
        ],
        [
            13814407,
            13835155
        ]
    ],
    "execute_cost": 59.282997131347656,
    "finish_time": 13835164,
    "limit_cost_by_ms": 47.339332580566406,
    "model_name": "vgg19",
    "recv_time": 13743236,
    "tag": "215",
    "total_cost_by_ms": 91.9280014038086,
    "wait_cost": 32.64500427246094
}
