{
    "child_model_execute_cost_by_ms": [
        2.8329999446868896,
        4.36899995803833
    ],
    "child_model_run_time": [
        [
            17537648,
            17540481
        ],
        [
            17540569,
            17544938
        ]
    ],
    "execute_cost": 7.201999664306641,
    "finish_time": 17544948,
    "limit_cost_by_ms": 6.170333385467529,
    "model_name": "yolov2",
    "recv_time": 17521910,
    "tag": "372",
    "total_cost_by_ms": 23.038000106811523,
    "wait_cost": 15.836000442504883
}
