{
    "child_model_execute_cost_by_ms": [
        18.941999435424805,
        18.333999633789063,
        20.406999588012695
    ],
    "child_model_run_time": [
        [
            19259480,
            19278422
        ],
        [
            19278471,
            19296805
        ],
        [
            19296825,
            19317232
        ]
    ],
    "execute_cost": 57.68299865722656,
    "finish_time": 19317239,
    "limit_cost_by_ms": 47.339332580566406,
    "model_name": "vgg19",
    "recv_time": 19226194,
    "tag": "444",
    "total_cost_by_ms": 91.04499816894531,
    "wait_cost": 33.36199951171875
}
