{
    "child_model_execute_cost_by_ms": [
        17.570999145507813,
        18.014999389648438,
        21.336000442504883
    ],
    "child_model_run_time": [
        [
            25988210,
            26005781
        ],
        [
            26005870,
            26023885
        ],
        [
            26023975,
            26045311
        ]
    ],
    "execute_cost": 56.9219970703125,
    "finish_time": 26045319,
    "limit_cost_by_ms": 47.339332580566406,
    "model_name": "vgg19",
    "recv_time": 25964635,
    "tag": "721",
    "total_cost_by_ms": 80.68399810791016,
    "wait_cost": 23.762001037597656
}
