{
    "child_model_execute_cost_by_ms": [
        15.241000175476074,
        9.241999626159668
    ],
    "child_model_run_time": [
        [
            15195890,
            15211131
        ],
        [
            15211177,
            15220419
        ]
    ],
    "execute_cost": 24.482999801635742,
    "finish_time": 15220427,
    "limit_cost_by_ms": 19.21299934387207,
    "model_name": "resnet50",
    "recv_time": 15177659,
    "tag": "324",
    "total_cost_by_ms": 42.768001556396484,
    "wait_cost": 18.285001754760742
}
