{
    "child_model_execute_cost_by_ms": [
        14.317000389099121,
        8.9350004196167
    ],
    "child_model_run_time": [
        [
            26804705,
            26819022
        ],
        [
            26819068,
            26828003
        ]
    ],
    "execute_cost": 23.25200080871582,
    "finish_time": 26828010,
    "limit_cost_by_ms": 19.21299934387207,
    "model_name": "resnet50",
    "recv_time": 26790605,
    "tag": "892",
    "total_cost_by_ms": 37.404998779296875,
    "wait_cost": 14.152997970581055
}
