{
    "child_model_execute_cost_by_ms": [
        15.237000465393066,
        9.428999900817871
    ],
    "child_model_run_time": [
        [
            27347945,
            27363182
        ],
        [
            27370519,
            27379948
        ]
    ],
    "execute_cost": 24.666000366210938,
    "finish_time": 27379955,
    "limit_cost_by_ms": 19.21299934387207,
    "model_name": "resnet50",
    "recv_time": 27347860,
    "tag": "919",
    "total_cost_by_ms": 32.095001220703125,
    "wait_cost": 7.4290008544921875
}
