{
    "child_model_execute_cost_by_ms": [
        18.406999588012695,
        17.618999481201172,
        20.082000732421875
    ],
    "child_model_run_time": [
        [
            11618841,
            11637248
        ],
        [
            11637339,
            11654958
        ],
        [
            11654977,
            11675059
        ]
    ],
    "execute_cost": 56.108001708984375,
    "finish_time": 11675068,
    "limit_cost_by_ms": 47.556331634521484,
    "model_name": "vgg19",
    "recv_time": 11618828,
    "tag": "120",
    "total_cost_by_ms": 56.2400016784668,
    "wait_cost": 0.13199996948242188
}
