{
    "child_model_execute_cost_by_ms": [
        14.486000061035156,
        9.192000389099121
    ],
    "child_model_run_time": [
        [
            15357900,
            15372386
        ],
        [
            15380043,
            15389235
        ]
    ],
    "execute_cost": 23.678001403808594,
    "finish_time": 15389240,
    "limit_cost_by_ms": 19.137666702270508,
    "model_name": "resnet50",
    "recv_time": 15357894,
    "tag": "279",
    "total_cost_by_ms": 31.34600067138672,
    "wait_cost": 7.667999267578125
}
