{
    "child_model_execute_cost_by_ms": [
        19.964000701904297,
        18.558000564575195,
        20.582000732421875
    ],
    "child_model_run_time": [
        [
            16593799,
            16613763
        ],
        [
            16621515,
            16640073
        ],
        [
            16640105,
            16660687
        ]
    ],
    "execute_cost": 59.10400390625,
    "finish_time": 16660696,
    "limit_cost_by_ms": 47.556331634521484,
    "model_name": "vgg19",
    "recv_time": 16571703,
    "tag": "332",
    "total_cost_by_ms": 88.99299621582031,
    "wait_cost": 29.888992309570313
}
