{
    "child_model_execute_cost_by_ms": [
        19.450000762939453,
        18.408000946044922,
        21.371999740600586
    ],
    "child_model_run_time": [
        [
            28375548,
            28394998
        ],
        [
            28395097,
            28413505
        ],
        [
            28446327,
            28467699
        ]
    ],
    "execute_cost": 59.230003356933594,
    "finish_time": 28467707,
    "limit_cost_by_ms": 47.556331634521484,
    "model_name": "vgg19",
    "recv_time": 28375385,
    "tag": "823",
    "total_cost_by_ms": 92.3219985961914,
    "wait_cost": 33.09199523925781
}
