{
    "child_model_execute_cost_by_ms": [
        19.014999389648438,
        17.399999618530273,
        20.284000396728516
    ],
    "child_model_run_time": [
        [
            31152434,
            31171449
        ],
        [
            31171545,
            31188945
        ],
        [
            31188965,
            31209249
        ]
    ],
    "execute_cost": 56.69900131225586,
    "finish_time": 31209258,
    "limit_cost_by_ms": 47.556331634521484,
    "model_name": "vgg19",
    "recv_time": 31152331,
    "tag": "938",
    "total_cost_by_ms": 56.926998138427734,
    "wait_cost": 0.227996826171875
}
