{
    "child_model_execute_cost_by_ms": [
        18.187999725341797,
        18.216999053955078,
        20.541000366210938
    ],
    "child_model_run_time": [
        [
            24300860,
            24319048
        ],
        [
            24319144,
            24337361
        ],
        [
            24337457,
            24357998
        ]
    ],
    "execute_cost": 56.94599914550781,
    "finish_time": 24358008,
    "limit_cost_by_ms": 47.409000396728516,
    "model_name": "vgg19",
    "recv_time": 24264560,
    "tag": "662",
    "total_cost_by_ms": 93.447998046875,
    "wait_cost": 36.50199890136719
}
