{
    "child_model_execute_cost_by_ms": [
        19.256999969482422,
        18.288999557495117,
        20.993000030517578
    ],
    "child_model_run_time": [
        [
            26918586,
            26937843
        ],
        [
            26946038,
            26964327
        ],
        [
            26972383,
            26993376
        ]
    ],
    "execute_cost": 58.538997650146484,
    "finish_time": 26993384,
    "limit_cost_by_ms": 47.409000396728516,
    "model_name": "vgg19",
    "recv_time": 26899165,
    "tag": "774",
    "total_cost_by_ms": 94.21900177001953,
    "wait_cost": 35.68000411987305
}
